LICENSE
MANIFEST.in
README.rst
setup.py
postnl/__init__.py
postnl/locations/__init__.py
postnl/locations/client.py
postnl/locations/settings.py
postnl/locations/transform.py
postnl/locations/utils.py
postnl/locations/tests/__init__.py
postnl_locations.egg-info/PKG-INFO
postnl_locations.egg-info/SOURCES.txt
postnl_locations.egg-info/dependency_links.txt
postnl_locations.egg-info/namespace_packages.txt
postnl_locations.egg-info/not-zip-safe
postnl_locations.egg-info/requires.txt
postnl_locations.egg-info/top_level.txt