Metadata-Version: 1.1
Name: postnl-locations
Version: 0.2.0
Summary: A Python wrapper for using the PostNL locations SOAP API
Home-page: https://github.com/maerteijn/python-postnl-locations
Author: Martijn Jacobs
Author-email: martijn@devopsconsulting.nl
License: BSD
Keywords: postnl locations pickuppoints
Platform: UNKNOWN
Classifier: Development Status :: 4 - Beta
Classifier: Environment :: Web Environment
Classifier: Intended Audience :: Developers
Classifier: License :: OSI Approved :: BSD License
Classifier: Operating System :: Unix
Classifier: Programming Language :: Python
Classifier: Programming Language :: Python :: 2
Classifier: Programming Language :: Python :: 2.7
Classifier: Programming Language :: Python :: 3
Classifier: Programming Language :: Python :: 3.5
Classifier: Topic :: Software Development :: Libraries
